<cei:cei xmlns:cei="http://www.monasterium.net/NS/cei">
   <cei:teiHeader>
      <cei:fileDesc>
         <cei:titleStmt>
            <cei:title type="main">ACK_735_I</cei:title>
         </cei:titleStmt>
         <cei:seriesStmt>
            <cei:title>NACR - German charters</cei:title>
         </cei:seriesStmt>
         <cei:sourceDesc>
            <cei:bibl>
               <cei:title type="main">ACK_735_I</cei:title><cei:idno type="Transkribus">192730</cei:idno><cei:idno type="external">NA</cei:idno>
            </cei:bibl>
         </cei:sourceDesc>
      </cei:fileDesc>
   </cei:teiHeader>
   
   
      
         
           <cei:tenor><cei:pb facs="#facs_1" n="1" id="img_0001"/><cei:pTenor facs="#facs_1_r1">
              
              
                    <cei:lb facs="#facs_1_r1l2" n="N001"/>Ich <cei:persName id="home_ger_211">Hainrich Grozz, schultheizz</cei:persName>, und wir die scheppfen der stat zu <cei:placeName>Nurnberg</cei:placeName> veriehen offenlichen mit disem brif, 
                    <cei:lb facs="#facs_1_r1l3" n="N002"/>daz fur uns kom in geriht <cei:persName id="home_ger_213">Ulrich Stromair</cei:persName> von wegen dez allerdurchleuchtigsten fursten, unsers genedigen herren
                    <cei:lb facs="#facs_1_r1l5" n="N003"/>hern <cei:persName id="home_ger_18">Karls, dez romischen kaisers und kunges zu <cei:placeName>Behaim</cei:placeName></cei:persName><cei:placeName/>, und erzeugt als reht, waz mit den ersamen mannen 
                    <cei:lb facs="#facs_1_r1l6" n="N004"/><cei:persName id="home_ger_217">Berhtolt, dem tucher</cei:persName>, mit <cei:persName id="home_ger_221">Peter Stromair</cei:persName> und mit <cei:persName id="home_ger_217">Hainrich, dem gewder</cei:persName>, die sagten auf ir ayde, dez sie des 
                    <cei:lb facs="#facs_1_r1l7" n="N005"/>geladen zewge, wem umb die zwen hof zu <cei:placeName>Heuchlingen</cei:placeName> gelegen, und umb die zwen hof zu <cei:placeName>Weizzenbach</cei:placeName> gelegen 
                    <cei:lb facs="#facs_1_r1l8" n="N006"/>die <cei:persName id="home_ger_222">Ulreich Winterstain, burger ze <cei:placeName>Nurnberg</cei:placeName></cei:persName><cei:placeName/>, gekauft het auf einen widerkauff von dem vesten ritter hern <cei:persName id="home_ger_181">Hainrich </cei:persName>
                    <cei:lb facs="#facs_1_r1l9" n="N007"/><cei:persName id="home_ger_213">vom <cei:placeName>Wildenstain</cei:placeName></cei:persName> umb funfhundert pfunt haller, ains und ahczig pfunt und vir und ahczig haller, als der 
                    <cei:lb facs="#facs_1_r1l10" n="N008"/>brif sagt, den er daruber het den die obgenanten zeugen gesehen heten, dez het der vorgenant <cei:persName id="home_ger_222">Ulrich Winterstain</cei:persName> 
                    <cei:lb facs="#facs_1_r1l12" n="N009"/>mit gesampter hant frawn <cei:persName id="home_ger_223">Agnesen, seiner elichen wirtinn</cei:persName>, veriehen und bechant, daz sie dieselben vir hof, als 
                    <cei:lb facs="#facs_1_r1l13" n="N010"/>sie hie vor geschriben sten unserm genedigen herren dem Romischen kaiser wider ze losen solten geben zu der 
                    <cei:lb facs="#facs_1_r1l14" n="N011"/>vesten ze dem <cei:placeName>Rotenberg</cei:placeName>, alz ainem kunge ze <cei:placeName>Behaim</cei:placeName> oder seinen erben und nachkumen, welches iares sie die 
                    <cei:lb facs="#facs_1_r1l15" n="N012"/>wider losen wollen, umb so vil gelcz, als hie vor benant ist, doch also daz die losung ie geschehen, sollt virzehen 
                    <cei:lb facs="#facs_1_r1l16" n="N013"/>tage vor lihtmesse oder virzehen tage darnach, als losung reht ist on gewerde, und dez zu urkund ist im dirr 
                    <cei:lb facs="#facs_1_r1l18" n="N014"/>brif mit urteil von geriht geben, versigelt mit dez gerihcz ze <cei:placeName>Nurnberg</cei:placeName> anhangendem insigel. Geben <cei:date value="99999999">an </cei:date>
                    <cei:lb facs="#facs_1_r1l19" n="N015"/><cei:date value="99999999">sant Ulrichs tage, nach Gotes gepurt drewzehenhundert jar und in dem sechczigistem jar</cei:date>.
            </cei:pTenor></cei:tenor>
         
      
   
</cei:cei>